rer.immersivereader-0.2.0-py3.10-nspkg.pth
rer/immersivereader/__init__.py
rer/immersivereader/configure.zcml
rer/immersivereader/interfaces.py
rer/immersivereader/permissions.zcml
rer/immersivereader/setuphandlers.py
rer/immersivereader/testing.py
rer/immersivereader/browser/__init__.py
rer/immersivereader/browser/configure.zcml
rer/immersivereader/browser/controlpanel.py
rer/immersivereader/browser/immersive_reader_viewlet.pt
rer/immersivereader/browser/viewlets.py
rer/immersivereader/browser/static/.gitkeep
rer/immersivereader/browser/static/package.json
rer/immersivereader/browser/static/yarn.lock
rer/immersivereader/browser/static/js/yarn.lock
rer/immersivereader/browser/static/js/dist/bundle-compiled.js
rer/immersivereader/browser/static/js/dist/bundle-compiled.js.map
rer/immersivereader/browser/static/js/dist/rer-immersive-reader-compiled.min.js
rer/immersivereader/browser/static/js/dist/rer-immersive-reader-compiled.min.js.map
rer/immersivereader/browser/static/js/src/index.js
rer/immersivereader/locales/README.rst
rer/immersivereader/locales/__init__.py
rer/immersivereader/locales/rer.immersivereader.pot
rer/immersivereader/locales/update.py
rer/immersivereader/locales/update.sh
rer/immersivereader/locales/it/LC_MESSAGES/rer.immersivereader.mo
rer/immersivereader/locales/it/LC_MESSAGES/rer.immersivereader.po
rer/immersivereader/profiles/default/browserlayer.xml
rer/immersivereader/profiles/default/catalog.xml
rer/immersivereader/profiles/default/controlpanel.xml
rer/immersivereader/profiles/default/metadata.xml
rer/immersivereader/profiles/default/rolemap.xml
rer/immersivereader/profiles/default/viewlets.xml
rer/immersivereader/profiles/default/registry/main.xml
rer/immersivereader/profiles/uninstall/browserlayer.xml
rer/immersivereader/profiles/uninstall/controlpanel.xml
rer/immersivereader/profiles/uninstall/registry.xml
rer/immersivereader/restapi/__init__.py
rer/immersivereader/restapi/configure.zcml
rer/immersivereader/restapi/controlpanel.py
rer.immersivereader-0.2.0.dist-info/LICENSE.GPL
rer.immersivereader-0.2.0.dist-info/LICENSE.rst
rer.immersivereader-0.2.0.dist-info/METADATA
rer.immersivereader-0.2.0.dist-info/WHEEL
rer.immersivereader-0.2.0.dist-info/entry_points.txt
rer.immersivereader-0.2.0.dist-info/namespace_packages.txt
rer.immersivereader-0.2.0.dist-info/top_level.txt
rer.immersivereader-0.2.0.dist-info/RECORD
