Metadata-Version: 2.1
Name: rer.immersivereader
Version: 0.2.0
Summary: Plone integration for Microsoft's Immersive Reader
Home-page: https://github.com/collective/rer.immersivereader
Author: RedTurtle Technology
Author-email: sviluppo@redturtle.it
License: GPL version 2
Project-URL: PyPI, https://pypi.python.org/pypi/rer.immersivereader
Project-URL: Source, https://github.com/collective/rer.immersivereader
Project-URL: Tracker, https://github.com/collective/rer.immersivereader/issues
Keywords: Python Plone CMS
Classifier: Development Status :: 5 - Production/Stable
Classifier: Environment :: Web Environment
Classifier: Framework :: Plone
Classifier: Framework :: Plone :: Addon
Classifier: Framework :: Plone :: 5.2
Classifier: Programming Language :: Python
Classifier: Programming Language :: Python :: 2.7
Classifier: Programming Language :: Python :: 3.7
Classifier: Operating System :: OS Independent
Classifier: License :: OSI Approved :: GNU General Public License v2 (GPLv2)
Requires-Python: >=3.7
License-File: LICENSE.GPL
License-File: LICENSE.rst
Requires-Dist: setuptools
Requires-Dist: plone.restapi
Provides-Extra: test
Requires-Dist: plone.app.testing ; extra == 'test'
Requires-Dist: plone.restapi[test] ; extra == 'test'
